{
 "attach_print": 0,
 "channel": "Email",
 "creation": "2024-02-24 17:57:26.816857",
 "days_in_advance": 0,
 "docstatus": 0,
 "doctype": "Notification",
 "document_type": "Gestion Des Utilisateurs",
 "enabled": 1,
 "event": "New",
 "idx": 0,
 "is_standard": 1,
 "message": "https://biomil.medigo.one/app/gestion-des-utilisateurs/{{ doc.name }}",
 "modified": "2024-03-04 10:40:46.434362",
 "modified_by": "Administrator",
 "module": "CRM Medigo",
 "name": "Gestion Utilisateurs",
 "owner": "Administrator",
 "recipients": [
  {
   "receiver_by_role": "System Manager"
  }
 ],
 "send_system_notification": 0,
 "send_to_all_assignees": 0,
 "subject": "Gestion Utilisateurs - {{ doc.name }}"
}