{
 "aggregate_function_based_on": "",
 "color": "#449CF0",
 "creation": "2024-02-08 15:40:20.156915",
 "docstatus": 0,
 "doctype": "Number Card",
 "document_type": "Visite Commerciale",
 "dynamic_filters_json": "[]",
 "filters_json": "[[\"Visite Commerciale\",\"workflow_state\",\"=\",\"Programm\u00e9e\",false]]",
 "function": "Count",
 "idx": 25,
 "is_public": 0,
 "is_standard": 1,
 "label": "VCI - Programm\u00e9es",
 "modified": "2024-02-09 18:32:21.401340",
 "modified_by": "Administrator",
 "module": "CRM Medigo",
 "name": "VCI - Programm\u00e9es",
 "owner": "Administrator",
 "parent_document_type": "",
 "report_function": "Sum",
 "show_percentage_stats": 0,
 "stats_time_interval": "Daily",
 "type": "Document Type"
}